fastapi_users_with_username/__init__.py
fastapi_users_with_username/exceptions.py
fastapi_users_with_username/fastapi_users.py
fastapi_users_with_username/jwt.py
fastapi_users_with_username/manager.py
fastapi_users_with_username/models.py
fastapi_users_with_username/openapi.py
fastapi_users_with_username/password.py
fastapi_users_with_username/py.typed
fastapi_users_with_username/schemas.py
fastapi_users_with_username/types.py
fastapi_users_with_username/authentication/__init__.py
fastapi_users_with_username/authentication/authenticator.py
fastapi_users_with_username/authentication/backend.py
fastapi_users_with_username/authentication/strategy/__init__.py
fastapi_users_with_username/authentication/strategy/base.py
fastapi_users_with_username/authentication/strategy/jwt.py
fastapi_users_with_username/authentication/strategy/redis.py
fastapi_users_with_username/authentication/strategy/db/__init__.py
fastapi_users_with_username/authentication/strategy/db/adapter.py
fastapi_users_with_username/authentication/strategy/db/models.py
fastapi_users_with_username/authentication/strategy/db/strategy.py
fastapi_users_with_username/authentication/transport/__init__.py
fastapi_users_with_username/authentication/transport/base.py
fastapi_users_with_username/authentication/transport/bearer.py
fastapi_users_with_username/authentication/transport/cookie.py
fastapi_users_with_username/db/__init__.py
fastapi_users_with_username/db/base.py
fastapi_users_with_username/router/__init__.py
fastapi_users_with_username/router/auth.py
fastapi_users_with_username/router/common.py
fastapi_users_with_username/router/oauth.py
fastapi_users_with_username/router/register.py
fastapi_users_with_username/router/reset.py
fastapi_users_with_username/router/users.py
fastapi_users_with_username/router/verify.py
fastapi_users_with_username-13.0.0.post1.dist-info/METADATA
fastapi_users_with_username-13.0.0.post1.dist-info/WHEEL
fastapi_users_with_username-13.0.0.post1.dist-info/licenses/LICENSE
fastapi_users_with_username-13.0.0.post1.dist-info/RECORD
